{"products":[{"id":"176314","title":"Love Pearl Earrings","handle":"love-pearl-earrings","description":"<p>About this product:</p>\n<ul>\n<li>Pinterest Inspired</li>\n<li>Sublte Design</li>\n<li>Base Colour- Gold<br>\n</li>\n</ul>\n<p>Pro Tip - Avoid contact with water and chemicals, and store with care for a long-lasting, shiny finish. </p>","body_html":"<p>About this product:</p>\n<ul>\n<li>Pinterest Inspired</li>\n<li>Sublte Design</li>\n<li>Base Colour- Gold<br>\n</li>\n</ul>\n<p>Pro Tip - Avoid contact with water and chemicals, and store with care for a long-lasting, shiny finish. </p>","vendor":"","product_type":"","created_at":"2026-02-11T19:18:43.950Z","updated_at":"2026-02-15T13:33:30.509Z","published_at":"2026-02-11T19:18:43.950Z","tags":["Earrings"],"variants":[{"id":"176314","product_id":"176314","title":"Default Title","price":"239.00","compare_at_price":"239.00","sku":"","barcode":"","position":1,"inventory_policy":"deny","inventory_quantity":9,"inventory_management":"LaunchMyStore","fulfillment_service":"manual","option1":"Default Title","option2":null,"option3":null,"taxable":true,"featured_image":{"id":null,"product_id":"f1f9ca8f-7382-4c16-af81-ba83dad8ba8d","src":"https://cdn.launchmystore.io/28860f10-e580-4c73-8c1f-a5227c0b34cf/file_1771162376767.jpeg","alt":"Love Pearl Earrings","width":1200,"height":1200},"available":true,"weight":0,"weight_unit":"kg","requires_shipping":true}],"images":[{"id":1,"product_id":"176314","position":1,"src":"https://cdn.launchmystore.io/28860f10-e580-4c73-8c1f-a5227c0b34cf/file_1771162376767.jpeg","alt":"Love Pearl Earrings","width":1200,"height":1200,"variant_ids":[]},{"id":2,"product_id":"176314","position":2,"src":"https://cdn.launchmystore.io/28860f10-e580-4c73-8c1f-a5227c0b34cf/file_1771162376624.jpeg","alt":"Love Pearl Earrings - Image 2","width":1200,"height":1200,"variant_ids":[]},{"id":3,"product_id":"176314","position":3,"src":"https://cdn.launchmystore.io/28860f10-e580-4c73-8c1f-a5227c0b34cf/file_1771162376658.jpeg","alt":"Love Pearl Earrings - Image 3","width":1200,"height":1200,"variant_ids":[]}],"options":[{"id":1,"product_id":"176314","name":"Title","position":1,"values":["Default Title"]}],"featured_image":"https://cdn.launchmystore.io/28860f10-e580-4c73-8c1f-a5227c0b34cf/file_1771162376767.jpeg","available":true,"price":"239.00","price_min":"239.00","price_max":"239.00"},{"id":"408580","title":"Bow & Heart Earrings","handle":"bow-heart-earrings","description":"<p>About this product:</p>\n<ul>\n<li>Pinterest Inspired</li>\n<li>Anti-Tarnish </li>\n<li>18k Gold Plated</li>\n<li>Base Colour- Gold</li>\n</ul>","body_html":"<p>About this product:</p>\n<ul>\n<li>Pinterest Inspired</li>\n<li>Anti-Tarnish </li>\n<li>18k Gold Plated</li>\n<li>Base Colour- Gold</li>\n</ul>","vendor":"","product_type":"","created_at":"2026-02-11T19:18:43.950Z","updated_at":"2026-02-20T07:56:23.240Z","published_at":"2026-02-11T19:18:43.950Z","tags":[],"variants":[{"id":"408580","product_id":"408580","title":"Default Title","price":"239.00","compare_at_price":"239.00","sku":"","barcode":"","position":1,"inventory_policy":"deny","inventory_quantity":5,"inventory_management":"LaunchMyStore","fulfillment_service":"manual","option1":"Default Title","option2":null,"option3":null,"taxable":true,"featured_image":{"id":null,"product_id":"c23c9e1b-dd0c-4790-9ae6-ee7dc894ab0d","src":"https://cdn.launchmystore.io/28860f10-e580-4c73-8c1f-a5227c0b34cf/file_1771162393993.jpeg","alt":"Bow & Heart Earrings","width":1200,"height":1200},"available":true,"weight":0,"weight_unit":"kg","requires_shipping":true}],"images":[{"id":1,"product_id":"408580","position":1,"src":"https://cdn.launchmystore.io/28860f10-e580-4c73-8c1f-a5227c0b34cf/file_1771162393993.jpeg","alt":"Bow & Heart Earrings","width":1200,"height":1200,"variant_ids":[]},{"id":2,"product_id":"408580","position":2,"src":"https://cdn.launchmystore.io/28860f10-e580-4c73-8c1f-a5227c0b34cf/file_1771162393995.jpeg","alt":"Bow & Heart Earrings - Image 2","width":1200,"height":1200,"variant_ids":[]},{"id":3,"product_id":"408580","position":3,"src":"https://cdn.launchmystore.io/28860f10-e580-4c73-8c1f-a5227c0b34cf/file_1771162393991.jpeg","alt":"Bow & Heart Earrings - Image 3","width":1200,"height":1200,"variant_ids":[]}],"options":[{"id":1,"product_id":"408580","name":"Title","position":1,"values":["Default Title"]}],"featured_image":"https://cdn.launchmystore.io/28860f10-e580-4c73-8c1f-a5227c0b34cf/file_1771162393993.jpeg","available":true,"price":"239.00","price_min":"239.00","price_max":"239.00"},{"id":"894564","title":"Gold Plated Pearl Earrings","handle":"gold-plated-pearl-earrings","description":"<p>About this product:</p>\n<ul>\n<li>Pinterest Inspired</li>\n<li>Sublte Design</li>\n<li>Base Colour- Gold<br>\n</li>\n</ul>\n<p>Pro Tip - Avoid contact with water and chemicals, and store with care for a long-lasting, shiny finish. </p>","body_html":"<p>About this product:</p>\n<ul>\n<li>Pinterest Inspired</li>\n<li>Sublte Design</li>\n<li>Base Colour- Gold<br>\n</li>\n</ul>\n<p>Pro Tip - Avoid contact with water and chemicals, and store with care for a long-lasting, shiny finish. </p>","vendor":"","product_type":"","created_at":"2026-02-11T19:18:43.950Z","updated_at":"2026-03-05T11:03:41.817Z","published_at":"2026-02-11T19:18:43.950Z","tags":[],"variants":[{"id":"894564","product_id":"894564","title":"Default Title","price":"239.00","compare_at_price":"239.00","sku":"","barcode":"","position":1,"inventory_policy":"deny","inventory_quantity":8,"inventory_management":"LaunchMyStore","fulfillment_service":"manual","option1":"Default Title","option2":null,"option3":null,"taxable":true,"featured_image":{"id":null,"product_id":"aa9348f4-e581-440c-ac12-ac8ba91ac630","src":"https://cdn.launchmystore.io/28860f10-e580-4c73-8c1f-a5227c0b34cf/file_1771162394455.jpeg","alt":"Gold Plated Pearl Earrings","width":1200,"height":1200},"available":true,"weight":0,"weight_unit":"kg","requires_shipping":true}],"images":[{"id":1,"product_id":"894564","position":1,"src":"https://cdn.launchmystore.io/28860f10-e580-4c73-8c1f-a5227c0b34cf/file_1771162394455.jpeg","alt":"Gold Plated Pearl Earrings","width":1200,"height":1200,"variant_ids":[]},{"id":2,"product_id":"894564","position":2,"src":"https://cdn.launchmystore.io/28860f10-e580-4c73-8c1f-a5227c0b34cf/file_1771162394480.jpeg","alt":"Gold Plated Pearl Earrings - Image 2","width":1200,"height":1200,"variant_ids":[]},{"id":3,"product_id":"894564","position":3,"src":"https://cdn.launchmystore.io/28860f10-e580-4c73-8c1f-a5227c0b34cf/file_1771162394974.jpeg","alt":"Gold Plated Pearl Earrings - Image 3","width":1200,"height":1200,"variant_ids":[]}],"options":[{"id":1,"product_id":"894564","name":"Title","position":1,"values":["Default Title"]}],"featured_image":"https://cdn.launchmystore.io/28860f10-e580-4c73-8c1f-a5227c0b34cf/file_1771162394455.jpeg","available":true,"price":"239.00","price_min":"239.00","price_max":"239.00"},{"id":"907112","title":"Spiral Earrings","handle":"spiral-earrings","description":"<p>About this product:-</p>\n<ul>\n<li>Trendy &amp; Quirky Statement Earrings</li>\n<li>Gold Finish</li>\n<li>Material- Zinc Alloy</li>\n<li>Pro Tip- Store properly for a longer shine</li>\n</ul>\n<p> </p>\n<p> </p>\n<p> </p>\n<p> </p>\n<p> </p>\n<p> </p>\n<p> </p>\n<p> </p>\n<p> </p>\n<p> </p>\n<p>;</p>\n<p> </p>","body_html":"<p>About this product:-</p>\n<ul>\n<li>Trendy &amp; Quirky Statement Earrings</li>\n<li>Gold Finish</li>\n<li>Material- Zinc Alloy</li>\n<li>Pro Tip- Store properly for a longer shine</li>\n</ul>\n<p> </p>\n<p> </p>\n<p> </p>\n<p> </p>\n<p> </p>\n<p> </p>\n<p> </p>\n<p> </p>\n<p> </p>\n<p> </p>\n<p>;</p>\n<p> </p>","vendor":"","product_type":"","created_at":"2026-02-11T19:18:43.946Z","updated_at":"2026-02-15T13:33:30.282Z","published_at":"2026-02-11T19:18:43.946Z","tags":[],"variants":[{"id":"907112","product_id":"907112","title":"Default Title","price":"199.00","compare_at_price":"299.00","sku":"","barcode":"","position":1,"inventory_policy":"deny","inventory_quantity":12,"inventory_management":"LaunchMyStore","fulfillment_service":"manual","option1":"Default Title","option2":null,"option3":null,"taxable":true,"featured_image":{"id":null,"product_id":"a96d175b-3269-48af-9157-ada7c9994084","src":"https://cdn.launchmystore.io/28860f10-e580-4c73-8c1f-a5227c0b34cf/file_1771162339344.jpeg","alt":"Spiral Earrings","width":1200,"height":1200},"available":true,"weight":0,"weight_unit":"kg","requires_shipping":true}],"images":[{"id":1,"product_id":"907112","position":1,"src":"https://cdn.launchmystore.io/28860f10-e580-4c73-8c1f-a5227c0b34cf/file_1771162339344.jpeg","alt":"Spiral Earrings","width":1200,"height":1200,"variant_ids":[]},{"id":2,"product_id":"907112","position":2,"src":"https://cdn.launchmystore.io/28860f10-e580-4c73-8c1f-a5227c0b34cf/file_1771162340167.jpeg","alt":"Spiral Earrings - Image 2","width":1200,"height":1200,"variant_ids":[]},{"id":3,"product_id":"907112","position":3,"src":"https://cdn.launchmystore.io/28860f10-e580-4c73-8c1f-a5227c0b34cf/file_1771162339971.jpeg","alt":"Spiral Earrings - Image 3","width":1200,"height":1200,"variant_ids":[]}],"options":[{"id":1,"product_id":"907112","name":"Title","position":1,"values":["Default Title"]}],"featured_image":"https://cdn.launchmystore.io/28860f10-e580-4c73-8c1f-a5227c0b34cf/file_1771162339344.jpeg","available":true,"price":"199.00","price_min":"199.00","price_max":"199.00"},{"id":"231637","title":"Korean Office Earrings","handle":"korean-office-earrings","description":"<p>About this product:</p>\n<ul>\n<li>Pinterest Inspired</li>\n<li>Sublte Design</li>\n<li>Base Colour- Gold</li>\n</ul>\n<p>Pro Tip - Avoid contact with water and chemicals, and store with care for a long-lasting, shiny finish.&nbsp;</p>","body_html":"<p>About this product:</p>\n<ul>\n<li>Pinterest Inspired</li>\n<li>Sublte Design</li>\n<li>Base Colour- Gold</li>\n</ul>\n<p>Pro Tip - Avoid contact with water and chemicals, and store with care for a long-lasting, shiny finish.&nbsp;</p>","vendor":"","product_type":"","created_at":"2026-02-11T19:18:43.950Z","updated_at":"2026-03-10T07:58:35.485Z","published_at":"2026-02-11T19:18:43.950Z","tags":["earrings"],"variants":[{"id":"231637","product_id":"231637","title":"Default Title","price":"99.00","compare_at_price":"199.00","sku":"","barcode":"","position":1,"inventory_policy":"deny","inventory_quantity":4,"inventory_management":"LaunchMyStore","fulfillment_service":"manual","option1":"Default Title","option2":null,"option3":null,"taxable":true,"featured_image":{"id":null,"product_id":"9eb850fa-1ba9-420d-be23-d8a8994f99c6","src":"https://cdn.launchmystore.io/28860f10-e580-4c73-8c1f-a5227c0b34cf/file_1771162406693.jpeg","alt":"Korean Office Earrings","width":1200,"height":1200},"available":true,"weight":"0.00","weight_unit":"kg","requires_shipping":true}],"images":[{"id":1,"product_id":"231637","position":1,"src":"https://cdn.launchmystore.io/28860f10-e580-4c73-8c1f-a5227c0b34cf/file_1771162406693.jpeg","alt":"Korean Office Earrings","width":1200,"height":1200,"variant_ids":[]},{"id":2,"product_id":"231637","position":2,"src":"https://cdn.launchmystore.io/28860f10-e580-4c73-8c1f-a5227c0b34cf/file_1771162406676.jpeg","alt":"Korean Office Earrings - Image 2","width":1200,"height":1200,"variant_ids":[]},{"id":3,"product_id":"231637","position":3,"src":"https://cdn.launchmystore.io/28860f10-e580-4c73-8c1f-a5227c0b34cf/file_1771162406717.jpeg","alt":"Korean Office Earrings - Image 3","width":1200,"height":1200,"variant_ids":[]}],"options":[{"id":1,"product_id":"231637","name":"Title","position":1,"values":["Default Title"]}],"featured_image":"https://cdn.launchmystore.io/28860f10-e580-4c73-8c1f-a5227c0b34cf/file_1771162406693.jpeg","available":true,"price":"99.00","price_min":"99.00","price_max":"99.00"},{"id":"966279","title":"Heart Lined Earrings","handle":"heart-lined-earrings","description":"<p>About this product:-</p>\n<ul>\n<li>Trendy &amp; Quirky Statement Earrings</li>\n<li>Gold Finish</li>\n<li>Material- Zinc Alloy</li>\n<li>Pro Tip- Store properly for a longer shine</li>\n</ul>\n<p> </p>\n<p> </p>\n<p> </p>\n<p> </p>\n<p> </p>\n<p> </p>\n<p> </p>\n<p> </p>\n<p> </p>\n<p> </p>\n<p>;</p>\n<p> </p>","body_html":"<p>About this product:-</p>\n<ul>\n<li>Trendy &amp; Quirky Statement Earrings</li>\n<li>Gold Finish</li>\n<li>Material- Zinc Alloy</li>\n<li>Pro Tip- Store properly for a longer shine</li>\n</ul>\n<p> </p>\n<p> </p>\n<p> </p>\n<p> </p>\n<p> </p>\n<p> </p>\n<p> </p>\n<p> </p>\n<p> </p>\n<p> </p>\n<p>;</p>\n<p> </p>","vendor":"","product_type":"","created_at":"2026-02-11T19:18:43.946Z","updated_at":"2026-02-20T07:56:23.225Z","published_at":"2026-02-11T19:18:43.946Z","tags":[],"variants":[{"id":"966279","product_id":"966279","title":"Default Title","price":"199.00","compare_at_price":"299.00","sku":"","barcode":"","position":1,"inventory_policy":"deny","inventory_quantity":12,"inventory_management":"LaunchMyStore","fulfillment_service":"manual","option1":"Default Title","option2":null,"option3":null,"taxable":true,"featured_image":{"id":null,"product_id":"9b176bf8-b3e6-4d12-83f1-ab5a4a2814fd","src":"https://cdn.launchmystore.io/28860f10-e580-4c73-8c1f-a5227c0b34cf/file_1771162345548.jpeg","alt":"Heart Lined Earrings","width":1200,"height":1200},"available":true,"weight":0,"weight_unit":"kg","requires_shipping":true}],"images":[{"id":1,"product_id":"966279","position":1,"src":"https://cdn.launchmystore.io/28860f10-e580-4c73-8c1f-a5227c0b34cf/file_1771162345548.jpeg","alt":"Heart Lined Earrings","width":1200,"height":1200,"variant_ids":[]},{"id":2,"product_id":"966279","position":2,"src":"https://cdn.launchmystore.io/28860f10-e580-4c73-8c1f-a5227c0b34cf/file_1771162346030.jpeg","alt":"Heart Lined Earrings - Image 2","width":1200,"height":1200,"variant_ids":[]},{"id":3,"product_id":"966279","position":3,"src":"https://cdn.launchmystore.io/28860f10-e580-4c73-8c1f-a5227c0b34cf/file_1771162346027.jpeg","alt":"Heart Lined Earrings - Image 3","width":1200,"height":1200,"variant_ids":[]}],"options":[{"id":1,"product_id":"966279","name":"Title","position":1,"values":["Default Title"]}],"featured_image":"https://cdn.launchmystore.io/28860f10-e580-4c73-8c1f-a5227c0b34cf/file_1771162345548.jpeg","available":true,"price":"199.00","price_min":"199.00","price_max":"199.00"},{"id":"565152","title":"Double Heart Earrings","handle":"double-heart-earrings","description":"<p>About this product:-</p>\n<ul>\n<li>Base Material- Alloy</li>\n<li>Base Colour- Golden</li>\n<li>Perfect for Glam Looks</li>\n<li>Lightweight </li>\n</ul>","body_html":"<p>About this product:-</p>\n<ul>\n<li>Base Material- Alloy</li>\n<li>Base Colour- Golden</li>\n<li>Perfect for Glam Looks</li>\n<li>Lightweight </li>\n</ul>","vendor":"","product_type":"","created_at":"2026-02-11T19:18:43.950Z","updated_at":"2026-02-20T07:56:23.216Z","published_at":"2026-02-11T19:18:43.950Z","tags":[],"variants":[{"id":"565152","product_id":"565152","title":"Default Title","price":"199.00","compare_at_price":"399.00","sku":"","barcode":"","position":1,"inventory_policy":"deny","inventory_quantity":6,"inventory_management":"LaunchMyStore","fulfillment_service":"manual","option1":"Default Title","option2":null,"option3":null,"taxable":true,"featured_image":{"id":null,"product_id":"953a545f-7ae2-4acb-972c-4018d7efea2f","src":"https://cdn.launchmystore.io/28860f10-e580-4c73-8c1f-a5227c0b34cf/file_1771162383566.jpeg","alt":"Double Heart Earrings","width":1200,"height":1200},"available":true,"weight":0,"weight_unit":"kg","requires_shipping":true}],"images":[{"id":1,"product_id":"565152","position":1,"src":"https://cdn.launchmystore.io/28860f10-e580-4c73-8c1f-a5227c0b34cf/file_1771162383566.jpeg","alt":"Double Heart Earrings","width":1200,"height":1200,"variant_ids":[]}],"options":[{"id":1,"product_id":"565152","name":"Title","position":1,"values":["Default Title"]}],"featured_image":"https://cdn.launchmystore.io/28860f10-e580-4c73-8c1f-a5227c0b34cf/file_1771162383566.jpeg","available":true,"price":"199.00","price_min":"199.00","price_max":"199.00"},{"id":"985710","title":"Tulips & Daisy Earrings","handle":"tulips-daisy-earrings","description":"<p>About this product:-</p>\n<ul>\n<li>Cute Summer Earrings </li>\n<li>Pinterest Inspired </li>\n<li>Affordable Earrings </li>\n<li>Base Material- Plastic</li>\n</ul>","body_html":"<p>About this product:-</p>\n<ul>\n<li>Cute Summer Earrings </li>\n<li>Pinterest Inspired </li>\n<li>Affordable Earrings </li>\n<li>Base Material- Plastic</li>\n</ul>","vendor":"","product_type":"","created_at":"2026-02-11T19:18:43.950Z","updated_at":"2026-02-15T13:33:30.584Z","published_at":"2026-02-11T19:18:43.950Z","tags":[],"variants":[{"id":417407,"product_id":"985710","title":"blue","price":"99.00","compare_at_price":"199.00","sku":"","barcode":"","position":1,"inventory_policy":"deny","inventory_quantity":5,"inventory_management":"LaunchMyStore","fulfillment_service":"manual","option1":"blue","option2":null,"option3":null,"taxable":true,"featured_image":{"id":null,"product_id":"8f402843-4ac3-4867-a151-7123784eba5c","src":"https://cdn.launchmystore.io/28860f10-e580-4c73-8c1f-a5227c0b34cf/file_1771162385648.jpeg","alt":"blue","width":1200,"height":1200},"available":true,"weight":0,"weight_unit":"kg","requires_shipping":true}],"images":[{"id":1,"product_id":"985710","position":1,"src":"https://cdn.launchmystore.io/28860f10-e580-4c73-8c1f-a5227c0b34cf/file_1771162385648.jpeg","alt":"Tulips & Daisy Earrings","width":1200,"height":1200,"variant_ids":[417407]},{"id":2,"product_id":"985710","position":2,"src":"https://cdn.launchmystore.io/28860f10-e580-4c73-8c1f-a5227c0b34cf/file_1771162385769.jpeg","alt":"Tulips & Daisy Earrings - Image 2","width":1200,"height":1200,"variant_ids":[]}],"options":[{"id":1,"product_id":"985710","name":"Color","position":1,"values":["blue"]}],"featured_image":"https://cdn.launchmystore.io/28860f10-e580-4c73-8c1f-a5227c0b34cf/file_1771162385648.jpeg","available":true,"price":"99.00","price_min":"99.00","price_max":"99.00"},{"id":"799493","title":"Medium Chunky Hoops","handle":"medium-chunky-hoops","description":"<p>About this product:-</p>\n<ul>\n<li>Trendy &amp; Subtle Everyday Earrings</li>\n<li>Gold Finish</li>\n<li>Material- Zinc Alloy</li>\n<li>Pro Tip- Store properly for a longer shine</li>\n</ul>\n<p> </p>\n<p> </p>\n<p> </p>\n<p> </p>\n<p> </p>\n<p> </p>\n<p> </p>\n<p> </p>\n<p> </p>\n<p> </p>\n<p>;</p>\n<p> </p>","body_html":"<p>About this product:-</p>\n<ul>\n<li>Trendy &amp; Subtle Everyday Earrings</li>\n<li>Gold Finish</li>\n<li>Material- Zinc Alloy</li>\n<li>Pro Tip- Store properly for a longer shine</li>\n</ul>\n<p> </p>\n<p> </p>\n<p> </p>\n<p> </p>\n<p> </p>\n<p> </p>\n<p> </p>\n<p> </p>\n<p> </p>\n<p> </p>\n<p>;</p>\n<p> </p>","vendor":"","product_type":"","created_at":"2026-02-11T19:18:43.946Z","updated_at":"2026-02-15T13:33:30.293Z","published_at":"2026-02-11T19:18:43.946Z","tags":[],"variants":[{"id":"799493","product_id":"799493","title":"Default Title","price":"199.00","compare_at_price":"299.00","sku":"","barcode":"","position":1,"inventory_policy":"deny","inventory_quantity":12,"inventory_management":"LaunchMyStore","fulfillment_service":"manual","option1":"Default Title","option2":null,"option3":null,"taxable":true,"featured_image":{"id":null,"product_id":"8d52b6ad-10db-4503-80d9-268d71bf4d81","src":"https://cdn.launchmystore.io/28860f10-e580-4c73-8c1f-a5227c0b34cf/file_1771162341546.jpeg","alt":"Medium Chunky Hoops","width":1200,"height":1200},"available":true,"weight":0,"weight_unit":"kg","requires_shipping":true}],"images":[{"id":1,"product_id":"799493","position":1,"src":"https://cdn.launchmystore.io/28860f10-e580-4c73-8c1f-a5227c0b34cf/file_1771162341546.jpeg","alt":"Medium Chunky Hoops","width":1200,"height":1200,"variant_ids":[]},{"id":2,"product_id":"799493","position":2,"src":"https://cdn.launchmystore.io/28860f10-e580-4c73-8c1f-a5227c0b34cf/file_1771162341548.jpeg","alt":"Medium Chunky Hoops - Image 2","width":1200,"height":1200,"variant_ids":[]},{"id":3,"product_id":"799493","position":3,"src":"https://cdn.launchmystore.io/28860f10-e580-4c73-8c1f-a5227c0b34cf/file_1771162341524.jpeg","alt":"Medium Chunky Hoops - Image 3","width":1200,"height":1200,"variant_ids":[]}],"options":[{"id":1,"product_id":"799493","name":"Title","position":1,"values":["Default Title"]}],"featured_image":"https://cdn.launchmystore.io/28860f10-e580-4c73-8c1f-a5227c0b34cf/file_1771162341546.jpeg","available":true,"price":"199.00","price_min":"199.00","price_max":"199.00"},{"id":"728058","title":"Mini Chunky Hoops","handle":"mini-chunky-hoops","description":"<p>About this product:-</p>\n<ul>\n<li>Trendy &amp; Subtle Everyday Earrings</li>\n<li>Gold Finish</li>\n<li>Material- Zinc Alloy</li>\n<li>Pro Tip- Store properly for a longer shine</li>\n</ul>\n<p> </p>\n<p> </p>\n<p> </p>\n<p> </p>\n<p> </p>\n<p> </p>\n<p> </p>\n<p> </p>\n<p> </p>\n<p> </p>\n<p>;</p>\n<p> </p>","body_html":"<p>About this product:-</p>\n<ul>\n<li>Trendy &amp; Subtle Everyday Earrings</li>\n<li>Gold Finish</li>\n<li>Material- Zinc Alloy</li>\n<li>Pro Tip- Store properly for a longer shine</li>\n</ul>\n<p> </p>\n<p> </p>\n<p> </p>\n<p> </p>\n<p> </p>\n<p> </p>\n<p> </p>\n<p> </p>\n<p> </p>\n<p> </p>\n<p>;</p>\n<p> </p>","vendor":"","product_type":"","created_at":"2026-02-11T19:18:43.946Z","updated_at":"2026-02-15T13:33:30.771Z","published_at":"2026-02-11T19:18:43.946Z","tags":[],"variants":[{"id":"728058","product_id":"728058","title":"Default Title","price":"199.00","compare_at_price":"100.00","sku":"","barcode":"","position":1,"inventory_policy":"deny","inventory_quantity":12,"inventory_management":"LaunchMyStore","fulfillment_service":"manual","option1":"Default Title","option2":null,"option3":null,"taxable":true,"featured_image":{"id":null,"product_id":"77d58557-f697-411f-babe-1a3068a81437","src":"https://cdn.launchmystore.io/28860f10-e580-4c73-8c1f-a5227c0b34cf/file_1771162403796.jpeg","alt":"Mini Chunky Hoops","width":1200,"height":1200},"available":true,"weight":0,"weight_unit":"kg","requires_shipping":true}],"images":[{"id":1,"product_id":"728058","position":1,"src":"https://cdn.launchmystore.io/28860f10-e580-4c73-8c1f-a5227c0b34cf/file_1771162403796.jpeg","alt":"Mini Chunky Hoops","width":1200,"height":1200,"variant_ids":[]},{"id":2,"product_id":"728058","position":2,"src":"https://cdn.launchmystore.io/28860f10-e580-4c73-8c1f-a5227c0b34cf/file_1771162403780.jpeg","alt":"Mini Chunky Hoops - Image 2","width":1200,"height":1200,"variant_ids":[]},{"id":3,"product_id":"728058","position":3,"src":"https://cdn.launchmystore.io/28860f10-e580-4c73-8c1f-a5227c0b34cf/file_1771162403778.jpeg","alt":"Mini Chunky Hoops - Image 3","width":1200,"height":1200,"variant_ids":[]}],"options":[{"id":1,"product_id":"728058","name":"Title","position":1,"values":["Default Title"]}],"featured_image":"https://cdn.launchmystore.io/28860f10-e580-4c73-8c1f-a5227c0b34cf/file_1771162403796.jpeg","available":true,"price":"199.00","price_min":"199.00","price_max":"199.00"},{"id":"142789","title":"Floria - Flower Earring","handle":"floria-flower-earring","description":"<p>About this product:</p>\n<ul>\n<li>Pinterest Inspired</li>\n<li>Anti-Tarnish&nbsp;</li>\n<li>18k Gold Plated</li>\n<li>Base Colour- Gold</li>\n</ul>","body_html":"<p>About this product:</p>\n<ul>\n<li>Pinterest Inspired</li>\n<li>Anti-Tarnish&nbsp;</li>\n<li>18k Gold Plated</li>\n<li>Base Colour- Gold</li>\n</ul>","vendor":"","product_type":"","created_at":"2026-02-11T19:18:43.953Z","updated_at":"2026-02-19T18:15:20.191Z","published_at":"2026-02-11T19:18:43.953Z","tags":[],"variants":[{"id":"142789","product_id":"142789","title":"Default Title","price":"199.00","compare_at_price":"239.00","sku":"","barcode":"","position":1,"inventory_policy":"deny","inventory_quantity":2,"inventory_management":"LaunchMyStore","fulfillment_service":"manual","option1":"Default Title","option2":null,"option3":null,"taxable":true,"featured_image":{"id":null,"product_id":"67ff579e-11e3-4b01-9b84-82930ceb59c6","src":"https://cdn.launchmystore.io/28860f10-e580-4c73-8c1f-a5227c0b34cf/file_1771162380140.jpeg","alt":"Floria - Flower Earring","width":1200,"height":1200},"available":true,"weight":"0.00","weight_unit":"kg","requires_shipping":true}],"images":[{"id":1,"product_id":"142789","position":1,"src":"https://cdn.launchmystore.io/28860f10-e580-4c73-8c1f-a5227c0b34cf/file_1771162380140.jpeg","alt":"Floria - Flower Earring","width":1200,"height":1200,"variant_ids":[]},{"id":2,"product_id":"142789","position":2,"src":"https://cdn.launchmystore.io/28860f10-e580-4c73-8c1f-a5227c0b34cf/file_1771162380651.jpeg","alt":"Floria - Flower Earring - Image 2","width":1200,"height":1200,"variant_ids":[]},{"id":3,"product_id":"142789","position":3,"src":"https://cdn.launchmystore.io/28860f10-e580-4c73-8c1f-a5227c0b34cf/file_1771162380190.jpeg","alt":"Floria - Flower Earring - Image 3","width":1200,"height":1200,"variant_ids":[]}],"options":[{"id":1,"product_id":"142789","name":"Title","position":1,"values":["Default Title"]}],"featured_image":"https://cdn.launchmystore.io/28860f10-e580-4c73-8c1f-a5227c0b34cf/file_1771162380140.jpeg","available":true,"price":"199.00","price_min":"199.00","price_max":"199.00"},{"id":"544107","title":"Water Drop Earrings","handle":"water-drop-earrings","description":"<p>About this product:-</p>\n<ul>\n<li>Trendy &amp; Quirky Statement Earrings</li>\n<li>Gold Finish</li>\n<li>Material- Zinc Alloy</li>\n<li>Pro Tip- Store properly for a longer shine</li>\n</ul>\n<p> </p>\n<p> </p>\n<p> </p>\n<p> </p>\n<p> </p>\n<p> </p>\n<p> </p>\n<p> </p>\n<p> </p>\n<p> </p>\n<p>;</p>\n<p> </p>","body_html":"<p>About this product:-</p>\n<ul>\n<li>Trendy &amp; Quirky Statement Earrings</li>\n<li>Gold Finish</li>\n<li>Material- Zinc Alloy</li>\n<li>Pro Tip- Store properly for a longer shine</li>\n</ul>\n<p> </p>\n<p> </p>\n<p> </p>\n<p> </p>\n<p> </p>\n<p> </p>\n<p> </p>\n<p> </p>\n<p> </p>\n<p> </p>\n<p>;</p>\n<p> </p>","vendor":"","product_type":"","created_at":"2026-02-11T19:18:43.946Z","updated_at":"2026-02-15T13:33:30.389Z","published_at":"2026-02-11T19:18:43.946Z","tags":[],"variants":[{"id":"544107","product_id":"544107","title":"Default Title","price":"239.00","compare_at_price":"339.00","sku":"","barcode":"","position":1,"inventory_policy":"deny","inventory_quantity":12,"inventory_management":"LaunchMyStore","fulfillment_service":"manual","option1":"Default Title","option2":null,"option3":null,"taxable":true,"featured_image":{"id":null,"product_id":"4ca33410-2633-4df7-9398-f4fc2556c1aa","src":"https://cdn.launchmystore.io/28860f10-e580-4c73-8c1f-a5227c0b34cf/file_1771162357555.jpeg","alt":"Water Drop Earrings","width":1200,"height":1200},"available":true,"weight":0,"weight_unit":"kg","requires_shipping":true}],"images":[{"id":1,"product_id":"544107","position":1,"src":"https://cdn.launchmystore.io/28860f10-e580-4c73-8c1f-a5227c0b34cf/file_1771162357555.jpeg","alt":"Water Drop Earrings","width":1200,"height":1200,"variant_ids":[]},{"id":2,"product_id":"544107","position":2,"src":"https://cdn.launchmystore.io/28860f10-e580-4c73-8c1f-a5227c0b34cf/file_1771162357398.jpeg","alt":"Water Drop Earrings - Image 2","width":1200,"height":1200,"variant_ids":[]},{"id":3,"product_id":"544107","position":3,"src":"https://cdn.launchmystore.io/28860f10-e580-4c73-8c1f-a5227c0b34cf/file_1771162357373.jpeg","alt":"Water Drop Earrings - Image 3","width":1200,"height":1200,"variant_ids":[]}],"options":[{"id":1,"product_id":"544107","name":"Title","position":1,"values":["Default Title"]}],"featured_image":"https://cdn.launchmystore.io/28860f10-e580-4c73-8c1f-a5227c0b34cf/file_1771162357555.jpeg","available":true,"price":"239.00","price_min":"239.00","price_max":"239.00"},{"id":"992358","title":"Red Heart & Bow Earrings","handle":"red-heart-bow-earrings","description":"<p>About this product:</p>\n<ul>\n<li>Pinterest Inspired</li>\n<li>Sublte Design</li>\n<li>Base Colour- Gold<br>\n</li>\n</ul>\n<p>Pro Tip - Avoid contact with water and chemicals, and store with care for a long-lasting, shiny finish. </p>","body_html":"<p>About this product:</p>\n<ul>\n<li>Pinterest Inspired</li>\n<li>Sublte Design</li>\n<li>Base Colour- Gold<br>\n</li>\n</ul>\n<p>Pro Tip - Avoid contact with water and chemicals, and store with care for a long-lasting, shiny finish. </p>","vendor":"","product_type":"","created_at":"2026-02-11T19:18:43.950Z","updated_at":"2026-02-15T13:33:30.769Z","published_at":"2026-02-11T19:18:43.950Z","tags":["Earrings"],"variants":[{"id":"992358","product_id":"992358","title":"Default Title","price":"149.00","compare_at_price":"149.00","sku":"","barcode":"","position":1,"inventory_policy":"deny","inventory_quantity":7,"inventory_management":"LaunchMyStore","fulfillment_service":"manual","option1":"Default Title","option2":null,"option3":null,"taxable":true,"featured_image":{"id":null,"product_id":"1804eba5-7c04-4b3f-ae86-129f09cc5075","src":"https://cdn.launchmystore.io/28860f10-e580-4c73-8c1f-a5227c0b34cf/file_1771162403262.jpeg","alt":"Red Heart & Bow Earrings","width":1200,"height":1200},"available":true,"weight":0,"weight_unit":"kg","requires_shipping":true}],"images":[{"id":1,"product_id":"992358","position":1,"src":"https://cdn.launchmystore.io/28860f10-e580-4c73-8c1f-a5227c0b34cf/file_1771162403262.jpeg","alt":"Red Heart & Bow Earrings","width":1200,"height":1200,"variant_ids":[]},{"id":2,"product_id":"992358","position":2,"src":"https://cdn.launchmystore.io/28860f10-e580-4c73-8c1f-a5227c0b34cf/file_1771162403258.jpeg","alt":"Red Heart & Bow Earrings - Image 2","width":1200,"height":1200,"variant_ids":[]},{"id":3,"product_id":"992358","position":3,"src":"https://cdn.launchmystore.io/28860f10-e580-4c73-8c1f-a5227c0b34cf/file_1771162403274.jpeg","alt":"Red Heart & Bow Earrings - Image 3","width":1200,"height":1200,"variant_ids":[]}],"options":[{"id":1,"product_id":"992358","name":"Title","position":1,"values":["Default Title"]}],"featured_image":"https://cdn.launchmystore.io/28860f10-e580-4c73-8c1f-a5227c0b34cf/file_1771162403262.jpeg","available":true,"price":"149.00","price_min":"149.00","price_max":"149.00"},{"id":"566197","title":"Nova Grunge Earrings","handle":"nova-grunge-earrings","description":"<p>About this product:-</p>\n<ul>\n<li>Premium Colour</li>\n<li>Base Colour- Silver </li>\n<li>Base Material- Alloy</li>\n<li>Trending Design</li>\n</ul>","body_html":"<p>About this product:-</p>\n<ul>\n<li>Premium Colour</li>\n<li>Base Colour- Silver </li>\n<li>Base Material- Alloy</li>\n<li>Trending Design</li>\n</ul>","vendor":"","product_type":"","created_at":"2026-02-11T19:18:43.950Z","updated_at":"2026-02-20T01:33:40.907Z","published_at":"2026-02-11T19:18:43.950Z","tags":[],"variants":[{"id":"566197","product_id":"566197","title":"Default Title","price":"99.00","compare_at_price":"199.00","sku":"","barcode":"","position":1,"inventory_policy":"deny","inventory_quantity":6,"inventory_management":"LaunchMyStore","fulfillment_service":"manual","option1":"Default Title","option2":null,"option3":null,"taxable":true,"featured_image":{"id":null,"product_id":"17c93ee5-ce4b-449e-a5bb-097a5b1f2e5e","src":"https://cdn.launchmystore.io/28860f10-e580-4c73-8c1f-a5227c0b34cf/file_1771162383267.jpeg","alt":"Nova Grunge Earrings","width":1200,"height":1200},"available":true,"weight":0,"weight_unit":"kg","requires_shipping":true}],"images":[{"id":1,"product_id":"566197","position":1,"src":"https://cdn.launchmystore.io/28860f10-e580-4c73-8c1f-a5227c0b34cf/file_1771162383267.jpeg","alt":"Nova Grunge Earrings","width":1200,"height":1200,"variant_ids":[]}],"options":[{"id":1,"product_id":"566197","name":"Title","position":1,"values":["Default Title"]}],"featured_image":"https://cdn.launchmystore.io/28860f10-e580-4c73-8c1f-a5227c0b34cf/file_1771162383267.jpeg","available":true,"price":"99.00","price_min":"99.00","price_max":"99.00"}]}